wgeasywall/01-WGEasyWall-IPSet.sh
wgeasywall/02-WGEasyWall-IPTable.sh
wgeasywall/NOTE.txt
wgeasywall/NOWG-NET-NEW.yaml
wgeasywall/NOWG-NET-OLD.yaml
wgeasywall/NOWG.graphml
wgeasywall/NOWGUpdate.graphml
wgeasywall/RaaCManifest/ACCEPT.yaml
wgeasywall/RaaCManifest/Conntrack.yaml
wgeasywall/RaaCManifest/DROP.yaml
wgeasywall/RaaCManifest/General.yaml
wgeasywall/RaaCManifest/LOG.yaml
wgeasywall/WGMode-Update.graphml
wgeasywall/WGMode.graphml
wgeasywall/WGNet1-U.graphml
wgeasywall/WGNet1-Updated.graphml
wgeasywall/WGNet1-dry-Updated.graphml
wgeasywall/WGNet2.graphml
wgeasywall/__init__.py
wgeasywall/cmd/__init__.py
wgeasywall/cmd/config/__init__.py
wgeasywall/cmd/config/generate.py
wgeasywall/cmd/config/view.py
wgeasywall/cmd/network/__init__.py
wgeasywall/cmd/network/initilize.py
wgeasywall/config.py
wgeasywall/errorCode.txt
wgeasywall/iptable.py
wgeasywall/main.py
wgeasywall/net-graph-new.yaml
wgeasywall/net-graph-old.yaml
wgeasywall/net-sample-broken.yaml
wgeasywall/net-sample-new.yaml
wgeasywall/net-sample.yaml
wgeasywall/net-update-new.yaml
wgeasywall/net-update-old.yaml
wgeasywall/net-wg.yaml
wgeasywall/net.graphml
wgeasywall/network-newG.graphml
wgeasywall/network.py
wgeasywall/networkRule.graphml
wgeasywall/networkRule2.graphml
wgeasywall/networkRuleBlackList.graphml
wgeasywall/networkRuleWhitelist.graphml
wgeasywall/ruleAsCode.py
wgeasywall/utils/IPtable/ipset.py
wgeasywall/utils/IPtable/iptable.py
wgeasywall/utils/IPtable/rule.py
wgeasywall/utils/IPtable/score.py
wgeasywall/utils/__init__.py
wgeasywall/utils/general/configParser.py
wgeasywall/utils/general/filedir.py
wgeasywall/utils/general/general.py
wgeasywall/utils/graphml/generate.py
wgeasywall/utils/graphml/parser.py
wgeasywall/utils/graphml/update.py
wgeasywall/utils/mongo/__init__.py
wgeasywall/utils/mongo/core/__init__.py
wgeasywall/utils/mongo/core/collection.py
wgeasywall/utils/mongo/core/connection.py
wgeasywall/utils/mongo/core/db.py
wgeasywall/utils/mongo/gridfsmongo.py
wgeasywall-0.1.1.dist-info/entry_points.txt
wgeasywall-0.1.1.dist-info/LICENSE
wgeasywall-0.1.1.dist-info/WHEEL
wgeasywall-0.1.1.dist-info/METADATA
wgeasywall-0.1.1.dist-info/RECORD
