Metadata-Version: 2.1
Name: wgeasywall
Version: 0.1.1
Summary: A CLI tool for managing WireGuard networks and IPTables by using GraphML
Author: Armin Aminian
Author-email: rmin.aminian@gmail.com
Requires-Python: >=3.8,<4.0
Classifier: Programming Language :: Python :: 3
Classifier: Programming Language :: Python :: 3.8
Classifier: Programming Language :: Python :: 3.9
Requires-Dist: PyYAML (>=5.4.1,<6.0.0)
Requires-Dist: coolname (>=1.1.0,<2.0.0)
Requires-Dist: deepdiff (>=5.5.0,<6.0.0)
Requires-Dist: donna25519 (>=0.1.1,<0.2.0)
Requires-Dist: ipaddr (>=2.2.0,<3.0.0)
Requires-Dist: netaddr (>=0.8.0,<0.9.0)
Requires-Dist: networkx (>=2.6.3,<3.0.0)
Requires-Dist: prettyprint (>=0.1.5,<0.2.0)
Requires-Dist: pydantic (>=1.8.2,<2.0.0)
Requires-Dist: pymongo (>=3.12.0,<4.0.0)
Requires-Dist: python-hosts (>=1.0.1,<2.0.0)
Requires-Dist: pyyed (>=1.4.3,<2.0.0)
Requires-Dist: tabulate (>=0.8.9,<0.9.0)
Requires-Dist: typer (>=0.3.2,<0.4.0)
